README.md
setup.py
maketoken/__init__.py
maketoken/makeToken.py
maketoken.egg-info/PKG-INFO
maketoken.egg-info/SOURCES.txt
maketoken.egg-info/dependency_links.txt
maketoken.egg-info/requires.txt
maketoken.egg-info/top_level.txt